abm_initialization_collection/__init__.py
abm_initialization_collection/__main__.py
abm_initialization_collection/coordinate/__init__.py
abm_initialization_collection/coordinate/filter_coordinate_bounds.py
abm_initialization_collection/coordinate/make_grid_coordinates.py
abm_initialization_collection/image/__init__.py
abm_initialization_collection/image/create_voronoi_image.py
abm_initialization_collection/image/get_image_bounds.py
abm_initialization_collection/image/plot_contact_sheet.py
abm_initialization_collection/image/select_fov_images.py
abm_initialization_collection/py.typed
abm_initialization_collection/sample/__init__.py
abm_initialization_collection/sample/exclude_selected_ids.py
abm_initialization_collection/sample/get_image_samples.py
abm_initialization_collection/sample/get_sample_indices.py
abm_initialization_collection/sample/include_selected_ids.py
abm_initialization_collection/sample/remove_edge_regions.py
abm_initialization_collection/sample/remove_unconnected_regions.py
abm_initialization_collection/sample/scale_sample_coordinates.py
abm_initialization_collection-0.7.0.dist-info/LICENSE
abm_initialization_collection-0.7.0.dist-info/METADATA
abm_initialization_collection-0.7.0.dist-info/WHEEL
abm_initialization_collection-0.7.0.dist-info/RECORD
